setup.py
src/git_remote_couch/__init__.py
src/git_remote_couch/tests.py
src/git_remote_couch.egg-info/PKG-INFO
src/git_remote_couch.egg-info/SOURCES.txt
src/git_remote_couch.egg-info/dependency_links.txt
src/git_remote_couch.egg-info/entry_points.txt
src/git_remote_couch.egg-info/namespace_packages.txt
src/git_remote_couch.egg-info/not-zip-safe
src/git_remote_couch.egg-info/requires.txt
src/git_remote_couch.egg-info/top_level.txt