Metadata-Version: 1.0
Name: git-remote-couch
Version: 0.1dev3
Summary: a git-remote-helper that allows you to push source code into a CouchDB
Home-page: http://github.com/peritus/git-remote-couch
Author: Filip Noetzel
Author-email: filip+pypi@j03.de
License: Beerware
Platform: UNKNOWN
Classifier: Development Status :: 2 - Pre-Alpha
Classifier: Environment :: Console
Classifier: Intended Audience :: Developers
Classifier: Intended Audience :: System Administrators
Classifier: Operating System :: MacOS :: MacOS X
Classifier: Operating System :: POSIX
Classifier: Operating System :: POSIX :: BSD
Classifier: Operating System :: POSIX :: Linux
Classifier: Topic :: Software Development :: Version Control
